__init__.py
plt_font_setup.py
ez2code-0.0.2.dist-info/LICENSE.txt
ez2code-0.0.2.dist-info/METADATA
ez2code-0.0.2.dist-info/WHEEL
ez2code-0.0.2.dist-info/top_level.txt
ez2code-0.0.2.dist-info/RECORD
